cloudformation_dynamodb_export/__init__.py
cloudformation_dynamodb_export/cfn2ddb.py
cloudformation_dynamodb_export/cfn_parser.py
cloudformation_dynamodb_export-0.2.3.dist-info/LICENSE
cloudformation_dynamodb_export-0.2.3.dist-info/METADATA
cloudformation_dynamodb_export-0.2.3.dist-info/WHEEL
cloudformation_dynamodb_export-0.2.3.dist-info/entry_points.txt
cloudformation_dynamodb_export-0.2.3.dist-info/top_level.txt
cloudformation_dynamodb_export-0.2.3.dist-info/RECORD
