Metadata-Version: 2.1
Name: cloudformation-dynamodb-export
Version: 0.2.3
Summary: Export DynamoDB definition in Cloudformation template files as json
Home-page: https://github.com/tomoya55/cloudformation-dynamodb-export
Author: tomoya55
Author-email: hiranotomoya@gmail.com
License: UNKNOWN
Keywords: aws cloudformation dynamodb
Platform: UNKNOWN
Classifier: Programming Language :: Python :: 3
Classifier: License :: OSI Approved :: MIT License
Classifier: Operating System :: OS Independent
Requires-Dist: awscli (>=1.16)
